sparqlfun/__init__.py
sparqlfun/cli.py
sparqlfun/config/endpoints.yaml
sparqlfun/config_schema.py
sparqlfun/data/jsonld/sparqlfun.context.jsonld
sparqlfun/data/jsonld/sparqlfun.jsonld
sparqlfun/data/jsonschema/sparqlfun.schema.json
sparqlfun/data/shacl/sparqlfun.shacl.ttl
sparqlfun/gocam_queries.py
sparqlfun/model.py
sparqlfun/query_engine.py
sparqlfun/resultset.py
sparqlfun/schema/biolink.yaml
sparqlfun/schema/chebi.yaml
sparqlfun/schema/config_schema.yaml
sparqlfun/schema/gocam.yaml
sparqlfun/schema/gocam_queries.yaml
sparqlfun/schema/omo.yaml
sparqlfun/schema/owl.yaml
sparqlfun/schema/rdf.yaml
sparqlfun/schema/relation_graph.yaml
sparqlfun/schema/resultset.yaml
sparqlfun/schema/ro.yaml
sparqlfun/schema/sparqlfun.yaml
sparqlfun/schema/ubergraph.yaml
sparqlfun/schema/uberon.yaml
sparqlfun/schema/uniprot.yaml
sparqlfun/schema/uniprot_queries.yaml
sparqlfun/sparql_util.py
sparqlfun-0.2.1.dist-info/entry_points.txt
sparqlfun-0.2.1.dist-info/LICENSE
sparqlfun-0.2.1.dist-info/WHEEL
sparqlfun-0.2.1.dist-info/METADATA
sparqlfun-0.2.1.dist-info/RECORD
