Metadata-Version: 2.1
Name: sparqlfun
Version: 0.2.1
Summary: SPARQL templates for LinkML
Home-page: https://github.com/linkml/sparqlfun
Author: cmungall
Author-email: cjm@berkeleybop.org
Requires-Python: >=3.9,<4.0
Classifier: Programming Language :: Python :: 3
Classifier: Programming Language :: Python :: 3.10
Classifier: Programming Language :: Python :: 3.9
Requires-Dist: Jinja2 (>=3.0.3,<4.0.0)
Requires-Dist: linkml-runtime (>=1.2.9,<2.0.0)
Requires-Dist: rdflib (>=6.1.1)
Project-URL: Documentation, https://github.com/linkml/sparqlfun
Project-URL: Repository, https://github.com/linkml/sparqlfun
